 [
    {
        "id": 1,
        "title": "قلوب ملونة",
        "description": "استمتع بتلوين دفتر “يوميات خالد” ن حيث يحتوي على أعمال يقوم بها خالد يومياً",
        "image": "/assets/img1.svg",
        "price": "50.00 ر.س"
    },
    {
        "id": 2,
        "title": "صندوق الحيوانات",
        "description": "في كل كتاب من سلسلة «صناديق فيزو» يحمل «فيزو» صندوقًا مختلفًا تخرج منه مفاجآت مدهشة،",
        "image": "/assets/img2.svg",
        "price": "50.00 ر.س"
    },
    {
        "id": 3,
        "title": "كل شيء عن المشاعر",
        "description": "يا تُرى كيف تشعر هذا الصباح؟ هذه الرحلة الاستكشافية في عالم المشاعر المتنوعة",
        "image": "/assets/img3.svg",
        "price": "50.00 ر.س"
    },
    {
        "id": 4,
        "title": "تفاحة - تفاحتان - ثلاث تفاحات",
        "description": "تم تصميم هذا الكتاب ليكون ملعبا واسعا يقضي فيه الطفل ووالديه أوقات ممتعة،",
        "image": "/assets/img4.svg",
        "price": "50.00 ر.س"
    },
    {
        "id": 5,
        "title": "فيزو المحترم",
        "description": "فيزو يرى أن بابا محترم جدًا لأنه يلبس بدلة وكرافاته فقرر أن يصبح محترم ولبس ملابس بابا.",
        "image": "/assets/img5.svg",
        "price": "50.00 ر.س"
    },
    {
        "id": 6,
        "title": " موسوعة للصغار جدا",
        "description": "- ألعاب متنوعة للطفل ليستمتع بمتابعة الموضوع. - أسئلة لتنمية التعليم التفاعلي للطفل.",
        "image": "/assets/img6.svg",
        "price": "50.00 ر.س"
    },
    {
        "id": 7,
        "title": "تعدد أشكال الحروف",
        "description": "سلسلة منهجية مبنية على أسس علمية، فبالإضافة إلى تدريب الطفل على المحاكاة",
        "image": "/assets/img7.svg",
        "price": "50.00 ر.س"
    },
    {
        "id": 8,
        "title": "صندوق الأرقام",
        "description": "في كل كتاب من سلسلة «صناديق فيزو» يحمل «فيزو» صندوقًا مختلفًا تخرج منه مفاجآت مدهشة",
        "image": "/assets/img8.svg",
        "price": "50.00 ر.س"
    }
]
